MANIFEST.in
README.html
README.txt
ez_setup.py
pdfsplit
pdfsplit.py
setup.cfg
setup.py
test_pdfsplit.py
pdfsplit.egg-info/PKG-INFO
pdfsplit.egg-info/SOURCES.txt
pdfsplit.egg-info/dependency_links.txt
pdfsplit.egg-info/requires.txt
pdfsplit.egg-info/top_level.txt
samples/genpdf.py
samples/test-odd.pdf
samples/test-reversed.pdf
samples/test-split-0..5.pdf
samples/test-split-0.pdf
samples/test-split.pdf
samples/test.pdf