Metadata-Version: 1.0
Name: pdfsplit
Version: 0.4.2
Summary: Split a PDF file or rearrange its pages into a new PDF file.
Home-page: http://www.dinu-gherman.net/
Author: Dinu Gherman
Author-email: gherman@darwin.in-berlin.de
License: GPL 3
Download-URL: http://www.dinu-gherman.net/tmp/pdfsplit-0.4.2.tar.gz
Keywords: PDF,slicing pages,rearraging pages
Platform: Posix
Platform: Windows
Classifier: Development Status :: 4 - Beta
Classifier: Environment :: Console
Classifier: Intended Audience :: End Users/Desktop
Classifier: Intended Audience :: Developers
Classifier: License :: OSI Approved :: GNU General Public License (GPL)
Classifier: Operating System :: MacOS :: MacOS X
Classifier: Operating System :: POSIX
Classifier: Operating System :: Microsoft :: Windows
Classifier: Programming Language :: Python
Classifier: Topic :: Utilities
Classifier: Topic :: Printing
